LICENSE
MANIFEST.in
README.md
requirements.txt
setup.py
tests/__init__.py
tests/process_test.py
textfeats/__init__.py
textfeats/columns.py
textfeats/count_process.py
textfeats/embedding_process.py
textfeats/process.py
textfeats/sentiment_process.py
textfeats/stemmer_process.py
textfeats.egg-info/PKG-INFO
textfeats.egg-info/SOURCES.txt
textfeats.egg-info/dependency_links.txt
textfeats.egg-info/not-zip-safe
textfeats.egg-info/requires.txt
textfeats.egg-info/top_level.txt