Metadata-Version: 2.1
Name: textfeats
Version: 0.1.3
Summary: A library for processing text features in a dataframe.
Home-page: https://github.com/8W9aG/text-features
Author: Will Sackfield
Author-email: will.sackfield@gmail.com
License: MIT
Keywords: features,text
Classifier: License :: OSI Approved :: MIT License
Classifier: Programming Language :: Python :: 3
License-File: LICENSE
Requires-Dist: pandas>=2.2.3
Requires-Dist: pyarrow>=20.0.0
Requires-Dist: sentence_transformers>=4.1.0
Requires-Dist: tqdm>=4.67.1
Requires-Dist: nltk>=3.9.1
Requires-Dist: textblob>=0.19.0
Requires-Dist: numpy>=1.26.4
